CHANGES.txt
LICENSE
MANIFEST.in
README.rst
setup.py
grigoriefflab/__init__.py
grigoriefflab/bibtex.py
grigoriefflab/constants.py
grigoriefflab/grigoriefflab_logo.png
grigoriefflab/protocols.conf
grigoriefflab/viewers.py
grigoriefflab/wizards.py
grigoriefflab/convert/__init__.py
grigoriefflab/convert/convert.py
grigoriefflab/convert/dataimport.py
grigoriefflab/protocols/__init__.py
grigoriefflab/protocols/program_ctffind.py
grigoriefflab/protocols/protocol_ctffind.py
grigoriefflab/protocols/protocol_ctftilt.py
grigoriefflab/protocols/protocol_frealign_base.py
grigoriefflab/protocols/protocol_import.py
grigoriefflab/protocols/protocol_magdist_correct.py
grigoriefflab/protocols/protocol_magdist_correct_coords.py
grigoriefflab/protocols/protocol_magdist_estimate.py
grigoriefflab/protocols/protocol_ml_classification.py
grigoriefflab/protocols/protocol_refinement.py
grigoriefflab/protocols/protocol_summovie.py
grigoriefflab/protocols/protocol_unblur.py
grigoriefflab/tests/__init__.py
grigoriefflab/tests/test_protocols_grigoriefflab.py
grigoriefflab/tests/test_protocols_grigoriefflab_magdist.py
grigoriefflab/tests/test_protocols_grigoriefflab_movies.py
scipion_em_grigoriefflab.egg-info/PKG-INFO
scipion_em_grigoriefflab.egg-info/SOURCES.txt
scipion_em_grigoriefflab.egg-info/dependency_links.txt
scipion_em_grigoriefflab.egg-info/top_level.txt