Metadata-Version: 1.0
Name: scipion-em-grigoriefflab
Version: 1.0.4
Summary: Grigoriefflab ready to use in scipion.
Home-page: https://github.com/scipion-em/scipion-em-grigoriefflab
Author: I2PC
Author-email: scipion@cnb.csic.es
License: UNKNOWN
Keywords: scipion cryoem imageprocessing scipion-1.2
Platform: UNKNOWN
